EEMs_toolkit.py
EEMs_toolkit-0.1.0.dist-info/METADATA
EEMs_toolkit-0.1.0.dist-info/WHEEL
EEMs_toolkit-0.1.0.dist-info/top_level.txt
EEMs_toolkit-0.1.0.dist-info/RECORD
