Metadata-Version: 2.1
Name: EEMs-toolkit
Version: 0.1.0
Summary: EEMs_toolkit是一个可以在Python上对三维荧光（EEM）进行平行因子分析（PARAFAC）的工具包，功能大致类似于MATLAB的drEEM toolbox。
Home-page: https://github.com/HHhyJJ/EEMs-toolkit
Author: HHhyJJ
License: MIT
Classifier: License :: OSI Approved :: MIT License
Classifier: Programming Language :: Python
Classifier: Programming Language :: Python :: 3
Classifier: Programming Language :: Python :: 3.9
Classifier: Programming Language :: Python :: Implementation :: CPython
Classifier: Programming Language :: Python :: Implementation :: PyPy
Requires-Python: >=3.9.0
Requires-Dist: numpy
Requires-Dist: scipy
Requires-Dist: pandas
Requires-Dist: matplotlib
Requires-Dist: tensorly
Requires-Dist: tlviz
Requires-Dist: joblib
Requires-Dist: openpyxl
